BetterBlackBoard/__init__.py
BetterBlackBoard/url.py
BetterBlackBoard/bb/__init__.py
BetterBlackBoard/bb/_course.py
BetterBlackBoard/bb/_system.py
BetterBlackBoard/bb/_task.py
BetterBlackBoard/cas/__init__.py
BetterBlackBoard/cas/_browser_login.py
BetterBlackBoard/cas/_client.py
BetterBlackBoard/cas/_info.py
betterblackboard-0.4.2.dist-info/licenses/LICENSE
betterblackboard-0.4.2.dist-info/METADATA
betterblackboard-0.4.2.dist-info/WHEEL
betterblackboard-0.4.2.dist-info/top_level.txt
betterblackboard-0.4.2.dist-info/RECORD
