Metadata-Version: 2.4
Name: BetterBlackBoard
Version: 0.4.2
Summary: Better BlackBoard for USTCer
Author-email: Rosaya <fishfinfan@mail.ustc.edu.cn>, XeF2 <xef2@mail.ustc.edu.cn>
Classifier: Development Status :: 4 - Beta
Classifier: Programming Language :: Python :: 3
Classifier: License :: OSI Approved :: MIT License
Classifier: Operating System :: OS Independent
Classifier: Topic :: Software Development :: Libraries :: Python Modules
Requires-Python: >=3.8
License-File: LICENSE
Requires-Dist: datetime
Requires-Dist: requests
Requires-Dist: fake-useragent
Requires-Dist: beautifulsoup4
Requires-Dist: typing_extensions>=4.0.0; python_version < "3.11"
Provides-Extra: browser
Requires-Dist: selenium; extra == "browser"
Dynamic: license-file
